ark_client/__init__.py
ark_client_certic-0.2.0.dist-info/LICENSE.txt
ark_client_certic-0.2.0.dist-info/METADATA
ark_client_certic-0.2.0.dist-info/WHEEL
ark_client_certic-0.2.0.dist-info/RECORD
