Metadata-Version: 2.1
Name: ark-client-certic
Version: 0.2.0
Summary: Ark Python client library
License: CECILL-C
Author: Mickaël Desfrênes
Author-email: mickael.desfrenes@unicaen.fr
Requires-Python: >=3.9
Classifier: License :: CeCILL-C Free Software License Agreement (CECILL-C)
Classifier: Programming Language :: Python :: 3
Classifier: Programming Language :: Python :: 3.9
Classifier: Programming Language :: Python :: 3.10
Classifier: Programming Language :: Python :: 3.11
Classifier: Programming Language :: Python :: 3.12
Requires-Dist: requests (>=2.31.0,<3.0.0)
